lyriq/__init__.py
lyriq/__main__.py
lyriq/cli.py
lyriq/lyriq.py
lyriq-1.6.0.dist-info/licenses/LICENSE
lyriq-1.6.0.dist-info/METADATA
lyriq-1.6.0.dist-info/WHEEL
lyriq-1.6.0.dist-info/entry_points.txt
lyriq-1.6.0.dist-info/top_level.txt
lyriq-1.6.0.dist-info/RECORD
