Metadata-Version: 2.4
Name: lyriq
Version: 1.6.0
Summary: A lightweight Python library designed to effortlessly fetch song lyrics.
Author-email: TN3W <tn3w@protonmail.com>
License-Expression: Apache-2.0
Project-URL: Homepage, https://github.com/tn3w/lyriq
Project-URL: Documentation, https://github.com/tn3w/lyriq/blob/master/README.md
Project-URL: Repository, https://github.com/tn3w/lyriq.git
Project-URL: Issues, https://github.com/tn3w/lyriq/issues
Keywords: lyrics,music,synchronization
Classifier: Development Status :: 5 - Production/Stable
Classifier: Environment :: Web Environment
Classifier: Intended Audience :: Developers
Classifier: Operating System :: OS Independent
Classifier: Programming Language :: Python
Classifier: Programming Language :: Python :: 3
Classifier: Programming Language :: Python :: 3.9
Classifier: Programming Language :: Python :: 3.10
Classifier: Programming Language :: Python :: 3.11
Classifier: Programming Language :: Python :: 3.12
Classifier: Programming Language :: Python :: 3.13
Classifier: Topic :: Internet :: WWW/HTTP
Classifier: Topic :: Multimedia :: Sound/Audio
Requires-Python: >=3.9
License-File: LICENSE
Provides-Extra: dev
Requires-Dist: black>=25.1.0; extra == "dev"
Requires-Dist: mypy>=1.16.1; extra == "dev"
Requires-Dist: pytest>=8.4.1; extra == "dev"
Requires-Dist: pytest-cov>=6.2.1; extra == "dev"
Dynamic: license-file
